LICENSE
MANIFEST.in
README.rst
requirements.txt
setup.py
bvl_api.egg-info/PKG-INFO
bvl_api.egg-info/SOURCES.txt
bvl_api.egg-info/dependency_links.txt
bvl_api.egg-info/requires.txt
bvl_api.egg-info/top_level.txt
bvlapi/__init__.py
bvlapi/__main__.py
bvlapi/api/__init__.py
bvlapi/api/call.py
bvlapi/api/settings.py
bvlapi/api/org/__init__.py
bvlapi/api/org/detail_by_guid.py
bvlapi/api/org/list.py
bvlapi/api/team/__init__.py
bvlapi/api/team/detail_by_guid.py
bvlapi/api/team/matches_by_guid.py
bvlapi/cli/__init__.py
bvlapi/cli/search.py
bvlapi/cli/teams.py
bvlapi/common/__init__.py
bvlapi/common/exceptions.py
bvlapi/common/http.py
bvlapi/data/__init__.py
bvlapi/data/parse.py
bvlapi/data/settings.py
bvlapi/data/competitions/__init__.py
bvlapi/data/competitions/competition.py
bvlapi/data/competitions/get.py
bvlapi/data/competitions/standing.py
bvlapi/data/matches/__init__.py
bvlapi/data/matches/get.py
bvlapi/data/matches/match.py
bvlapi/data/organizations/__init__.py
bvlapi/data/organizations/get.py
bvlapi/data/organizations/organization.py
bvlapi/data/teams/__init__.py
bvlapi/data/teams/get.py
bvlapi/data/teams/team.py
bvlapi/guid/__init__.py
bvlapi/guid/club.py
bvlapi/guid/team.py
tests/bvlapi/__init__.py
tests/bvlapi/api/__init__.py
tests/bvlapi/api/test_call.py
tests/bvlapi/api/test_org.py
tests/bvlapi/api/test_team.py
tests/bvlapi/cli/__init__.py
tests/bvlapi/cli/test_search.py
tests/bvlapi/cli/test_teams.py
tests/bvlapi/common/__init__.py
tests/bvlapi/common/test_http.py
tests/bvlapi/data/__init__.py
tests/bvlapi/data/test_competitions.py
tests/bvlapi/data/test_matches.py
tests/bvlapi/data/test_organizations.py
tests/bvlapi/data/test_parse.py
tests/bvlapi/data/test_teams.py
tests/bvlapi/guid/__init__.py
tests/bvlapi/guid/test_club.py
tests/bvlapi/guid/test_team.py
tests/files/__init__.py