Metadata-Version: 2.1
Name: bvl-api
Version: 0.6.0
Summary: Used to retrieve data about Flemish basketball competitions using the public API of Basketbal Vlaanderen.
Home-page: https://github.com/alanverresen/bvl-api
Author: Alan Verresen
Author-email: dev@alanverresen.com
License: MIT
Keywords: basketball,Flanders,Belgium,API
Platform: UNKNOWN
Classifier: Development Status :: 3 - Alpha
Classifier: License :: OSI Approved :: MIT License
Classifier: Programming Language :: Python :: 3
Classifier: Programming Language :: Python :: 3.6
Classifier: Programming Language :: Python :: 3.7
Classifier: Programming Language :: Python :: 3.8
Classifier: Programming Language :: Python :: 3.9
Requires-Python: >=3.6
License-File: LICENSE
